mixlora/__init__.py
mixlora/config.py
mixlora/lora_linear.py
mixlora/model.py
mixlora/prompter.py
mixlora/utils.py
mixlora-0.2.3.dist-info/LICENSE
mixlora-0.2.3.dist-info/METADATA
mixlora-0.2.3.dist-info/WHEEL
mixlora-0.2.3.dist-info/top_level.txt
mixlora-0.2.3.dist-info/RECORD
