Metadata-Version: 2.1
Name: mixlora
Version: 0.2.3
Summary: State-of-the-art Parameter-Efficient MoE Fine-tuning Method
Project-URL: Homepage, https://github.com/TUDB-Labs/MixLoRA
Project-URL: Bug Tracker, https://github.com/TUDB-Labs/MixLoRA/issues
Classifier: Programming Language :: Python :: 3
Classifier: License :: OSI Approved :: Apache Software License
Classifier: Operating System :: OS Independent
Requires-Python: >=3.8
License-File: LICENSE
Requires-Dist: torch >=2.2.0
Requires-Dist: transformers >=4.43.0
Requires-Dist: huggingface-hub
